alsssp/__init__.py
alsssp/algorithms.py
alsssp/core.py
alsssp/learning.py
alsssp/memory.py
turbo_dijkstra-1.0.0.dist-info/licenses/LICENSE
turbo_dijkstra-1.0.0.dist-info/METADATA
turbo_dijkstra-1.0.0.dist-info/WHEEL
turbo_dijkstra-1.0.0.dist-info/top_level.txt
turbo_dijkstra-1.0.0.dist-info/RECORD
