Metadata-Version: 2.4
Name: turbo-dijkstra
Version: 1.0.0
Summary: ALSSSP: Adaptive Learning Single-Source Shortest Path - 50x faster Dijkstra
Home-page: https://github.com/RaiAnk/turbo-dijkstra
Author: Dr. Ankush Rai
Author-email: "Dr. Ankush Rai" <ankushrai@bitdurg.ac.in>
Maintainer-email: "Dr. Ankush Rai" <ankushrai@bitdurg.ac.in>
License: MIT
Project-URL: Homepage, https://github.com/RaiAnk/turbo-dijkstra
Project-URL: Documentation, https://github.com/RaiAnk/turbo-dijkstra#readme
Project-URL: Repository, https://github.com/RaiAnk/turbo-dijkstra
Project-URL: Issues, https://github.com/RaiAnk/turbo-dijkstra/issues
Project-URL: YouTube, https://youtu.be/HHgXiHJqJDU
Keywords: shortest-path,dijkstra,graph-algorithms,bidirectional-search,pathfinding,optimization,routing,navigation,turbo-dijkstra,alsssp
Classifier: Development Status :: 4 - Beta
Classifier: Intended Audience :: Developers
Classifier: Intended Audience :: Science/Research
Classifier: License :: OSI Approved :: MIT License
Classifier: Operating System :: OS Independent
Classifier: Programming Language :: Python :: 3
Classifier: Programming Language :: Python :: 3.8
Classifier: Programming Language :: Python :: 3.9
Classifier: Programming Language :: Python :: 3.10
Classifier: Programming Language :: Python :: 3.11
Classifier: Programming Language :: Python :: 3.12
Classifier: Topic :: Scientific/Engineering
Classifier: Topic :: Scientific/Engineering :: Mathematics
Classifier: Topic :: Scientific/Engineering :: Artificial Intelligence
Classifier: Topic :: Software Development :: Libraries :: Python Modules
Requires-Python: >=3.8
License-File: LICENSE
Requires-Dist: numpy>=1.20.0
Provides-Extra: dev
Requires-Dist: pytest>=7.0.0; extra == "dev"
Requires-Dist: pytest-cov>=4.0.0; extra == "dev"
Provides-Extra: experiments
Requires-Dist: matplotlib>=3.5.0; extra == "experiments"
Requires-Dist: seaborn>=0.12.0; extra == "experiments"
Requires-Dist: pandas>=1.4.0; extra == "experiments"
Requires-Dist: networkx>=2.8.0; extra == "experiments"
Dynamic: author
Dynamic: home-page
Dynamic: license-file
Dynamic: requires-python
